{"id":6,"imageSource":"../img/witcher_6.png","genre":"Фэнтези","mark":4.0,"name":"Ведьмак: Башня Ласточки","author":"А. Сапковский","description":"Цири чудом избегает неминуемой гибели. По её следам идут могущественные враги. Чародейка, которая собиралась ей помощь, сама попадает в ужасную беду. Ведьмак по-прежнему не укрыл девушку под своим крылом, хотя продолжает искать её всюду. Остается одна надежда: укрыться в волшебной Башне Ласточки, куда теперь устремляется Цири.","sameBookList":[{"id":1,"name":"Ведьмак: Последнее желание"},{"id":2,"name":"Ведьмак: Меч предназначения"},{"id":3,"name":"Ведьмак: Кровь эльфов"},{"id":4,"name":"Ведьмак: Час презрения"},{"id":5,"name":"Ведьмак: Крещение огнём"},{"id":7,"name":"Ведьмак: Владычица озера"}]}